fastapirestclient/__init__.py
fastapirestclient/client.py
fastapirestclient/exceptions.py
fastapirestclient/utils.py
fastapirestclient-0.3.0.dist-info/METADATA
fastapirestclient-0.3.0.dist-info/WHEEL
fastapirestclient-0.3.0.dist-info/RECORD
